Metadata-Version: 2.1
Name: py2xml
Version: 1.0.5
Summary: Write XML with Pythonic Code
Home-page: https://github.com/am230/py2xml
Author: am230
Author-email: am.230@outlook.jp
License: MIT Licence
Keywords: javascript,convert,translator
Platform: any
Requires: strbuilder
License-File: LICENSE
